cst_micro_chassis/__init__.py
cst_micro_chassis/chassis.py
cst_micro_chassis/logging.py
cst_micro_chassis/resources.py
cst_micro_chassis/utils.py
cst_micro_chassis-0.1.0.dist-info/LICENSE
cst_micro_chassis-0.1.0.dist-info/METADATA
cst_micro_chassis-0.1.0.dist-info/WHEEL
cst_micro_chassis-0.1.0.dist-info/top_level.txt
cst_micro_chassis-0.1.0.dist-info/RECORD
