Metadata-Version: 2.1
Name: cst-micro-chassis
Version: 0.1.0
Summary: Microservices chassis pattern library
Home-page: https://pypi.org/project/cst-micro-chassis/
Author: cst
Author-email: nicolae.natrapeiu@cyber-solutions.com
License: MIT
Platform: UNKNOWN
Classifier: Programming Language :: Python
Classifier: Programming Language :: Python :: 3.7
Classifier: Programming Language :: Python :: Implementation :: CPython
Classifier: License :: OSI Approved :: MIT License
Requires-Python: >=3.7
Requires-Dist: flask (==1.1.*)
Requires-Dist: flask-restful (==0.3.*)
